MANIFEST.in
README.md
setup.py
colifrapy/__init__.py
colifrapy/cacher.py
colifrapy/commander.py
colifrapy/hub.py
colifrapy/logger.py
colifrapy/model.py
colifrapy/scaffolder.py
colifrapy/settings.py
colifrapy.egg-info/PKG-INFO
colifrapy.egg-info/SOURCES.txt
colifrapy.egg-info/dependency_links.txt
colifrapy.egg-info/entry_points.txt
colifrapy.egg-info/not-zip-safe
colifrapy.egg-info/requires.txt
colifrapy.egg-info/top_level.txt
colifrapy/templates/basic.tpl
colifrapy/templates/controller.tpl
colifrapy/templates/gitignore.tpl
colifrapy/templates/main.tpl
colifrapy/templates/model.tpl
colifrapy/templates/readme.tpl
colifrapy/templates/requirements.tpl
colifrapy/templates/settings.tpl
colifrapy/templates/settings.yml
colifrapy/templates/strings.tpl
colifrapy/templates/strings.yml
colifrapy/tools/__init__.py
colifrapy/tools/colorize.py
colifrapy/tools/decorators.py
colifrapy/tools/flavors.py
colifrapy/tools/renderer.py
colifrapy/tools/utilities.py